mkdocs_mermaid_to_image/__init__.py
mkdocs_mermaid_to_image/_version.py
mkdocs_mermaid_to_image/config.py
mkdocs_mermaid_to_image/exceptions.py
mkdocs_mermaid_to_image/image_generator.py
mkdocs_mermaid_to_image/logging_config.py
mkdocs_mermaid_to_image/markdown_processor.py
mkdocs_mermaid_to_image/mermaid_block.py
mkdocs_mermaid_to_image/plugin.py
mkdocs_mermaid_to_image/processor.py
mkdocs_mermaid_to_image/types.py
mkdocs_mermaid_to_image/utils.py
mkdocs_mermaid_to_image-1.3.1.dist-info/METADATA
mkdocs_mermaid_to_image-1.3.1.dist-info/WHEEL
mkdocs_mermaid_to_image-1.3.1.dist-info/entry_points.txt
mkdocs_mermaid_to_image-1.3.1.dist-info/licenses/LICENSE
mkdocs_mermaid_to_image-1.3.1.dist-info/RECORD
