Metadata-Version: 2.4
Name: mkdocs-mermaid-to-image
Version: 1.3.1
Summary: MkDocs plugin to preprocess Mermaid diagrams into static images
Project-URL: Homepage, https://github.com/nuitsjp/mkdocs-mermaid-to-image
Project-URL: Bug Reports, https://github.com/nuitsjp/mkdocs-mermaid-to-image/issues
Project-URL: Source, https://github.com/nuitsjp/mkdocs-mermaid-to-image
Author: nuitsjp
License: MIT
License-File: LICENSE
Keywords: diagram,mermaid,mkdocs,preprocessing,static-generation
Classifier: Development Status :: 4 - Beta
Classifier: Intended Audience :: Developers
Classifier: License :: OSI Approved :: MIT License
Classifier: Programming Language :: Python :: 3
Classifier: Programming Language :: Python :: 3.9
Classifier: Programming Language :: Python :: 3.10
Classifier: Programming Language :: Python :: 3.11
Classifier: Programming Language :: Python :: 3.12
Classifier: Topic :: Documentation
Classifier: Topic :: Text Processing :: Markup
Requires-Python: >=3.9
Requires-Dist: mkdocs-material>=8.0.0
Requires-Dist: mkdocs>=1.4.0
Requires-Dist: numpy>=1.20.0
Requires-Dist: pillow>=11.3.0
Provides-Extra: dev
Requires-Dist: bandit>=1.7.0; extra == 'dev'
Requires-Dist: hypothesis>=6.0.0; extra == 'dev'
Requires-Dist: mkdocs-to-pdf>=0.10.1; extra == 'dev'
Requires-Dist: mypy>=1.10.0; extra == 'dev'
Requires-Dist: pip-audit>=2.6.0; extra == 'dev'
Requires-Dist: pre-commit>=3.7.0; extra == 'dev'
Requires-Dist: pytest-cov>=5.0.0; extra == 'dev'
Requires-Dist: pytest-xdist>=3.5.0; extra == 'dev'
Requires-Dist: pytest>=8.0.0; extra == 'dev'
Requires-Dist: ruff>=0.4.0; extra == 'dev'
Requires-Dist: twine>=5.0.0; extra == 'dev'
Provides-Extra: docs
Requires-Dist: myst-parser>=2.0.0; extra == 'docs'
Requires-Dist: sphinx-autodoc-typehints>=2.0.0; extra == 'docs'
Requires-Dist: sphinx-rtd-theme>=2.0.0; extra == 'docs'
Requires-Dist: sphinx>=7.0.0; extra == 'docs'
